inspect_wandb/__init__.py
inspect_wandb/_registry.py
inspect_wandb/exceptions.py
inspect_wandb/providers.py
inspect_wandb/config/__init__.py
inspect_wandb/config/extras_manager.py
inspect_wandb/config/wandb_settings_source.py
inspect_wandb/config/settings/__init__.py
inspect_wandb/config/settings/base.py
inspect_wandb/config/settings/models.py
inspect_wandb/config/settings/weave.py
inspect_wandb/models/__init__.py
inspect_wandb/models/hooks.py
inspect_wandb/shared/__init__.py
inspect_wandb/shared/utils.py
inspect_wandb/viz/__init__.py
inspect_wandb/viz/inspect_viz_writer.py
inspect_wandb/weave/__init__.py
inspect_wandb/weave/hooks.py
inspect_wandb/weave/utils.py
inspect_wandb/weave/autopatcher/__init__.py
inspect_wandb/weave/autopatcher/inspect.py
inspect_wandb/weave/autopatcher/patcher.py
inspect_wandb/weave/autopatcher/plan.py
inspect_wandb/weave/autopatcher/scorer.py
inspect_wandb-0.2.1.dist-info/METADATA
inspect_wandb-0.2.1.dist-info/WHEEL
inspect_wandb-0.2.1.dist-info/entry_points.txt
inspect_wandb-0.2.1.dist-info/top_level.txt
inspect_wandb-0.2.1.dist-info/RECORD
