Metadata-Version: 2.4
Name: inspect_wandb
Version: 0.2.1
Summary: InspectAI <-> Weights and Biases integration
Author-email: Daniel Polatajko <danielpolatajko@gmail.com>, Qi Guo <special0831qi@gmail.com>, Matan Shtepel <matan.shtepel@gmail.com>
Project-URL: Homepage, https://github.com/DanielPolatajko/inspect_wandb
Project-URL: Issues, https://github.com/DanielPolatajko/inspect_wandb/issues
Project-URL: Documentation, https://inspect-wandb.readthedocs.io/en/latest/
Classifier: Programming Language :: Python :: 3
Classifier: Operating System :: OS Independent
Requires-Python: >=3.11
Requires-Dist: inspect_ai>=0.3.154
Requires-Dist: pydantic<3,>=2.12
Requires-Dist: pydantic-settings
Requires-Dist: wandb
Provides-Extra: weave
Requires-Dist: weave>=0.52.17; extra == "weave"
Provides-Extra: viz
Requires-Dist: inspect-viz; extra == "viz"
Requires-Dist: playwright; extra == "viz"
